pyproj_inspector/__init__.py
pyproj_inspector/build_utils.py
pyproj_inspector/cli.py
pyproj_inspector/inspector.py
pyproj_inspector/packaging_utils.py
pyproj_inspector-0.1.2.dist-info/METADATA
pyproj_inspector-0.1.2.dist-info/WHEEL
pyproj_inspector-0.1.2.dist-info/top_level.txt
pyproj_inspector-0.1.2.dist-info/RECORD
