Metadata-Version: 2.4
Name: pyproj_inspector
Version: 0.1.2
Summary: Analyze and package Python projects
Author: Avi Twil
License: MIT
Classifier: Programming Language :: Python :: 3
Classifier: License :: OSI Approved :: MIT License
Classifier: Operating System :: OS Independent
Requires-Python: >=3.8
